r2ds_api/__init__.py
r2ds_api/r2ds.py
r2ds_api-0.1.2.dist-info/DESCRIPTION.rst
r2ds_api-0.1.2.dist-info/METADATA
r2ds_api-0.1.2.dist-info/RECORD
r2ds_api-0.1.2.dist-info/WHEEL
r2ds_api-0.1.2.dist-info/metadata.json
r2ds_api-0.1.2.dist-info/top_level.txt
