Metadata-Version: 2.0
Name: r2ds-api
Version: 0.1.2
Summary: R2DS Python API
Home-page: https://github.com/tonkworks/r2ds_api
Author: Kevin Dagostino
Author-email: kevin@tonkworks.com
License: MIT license
Keywords: r2ds_api
Platform: UNKNOWN
Classifier: Development Status :: 2 - Pre-Alpha
Classifier: Intended Audience :: Developers
Classifier: License :: OSI Approved :: MIT License
Classifier: Natural Language :: English
Classifier: Programming Language :: Python :: 2
Classifier: Programming Language :: Python :: 2.7
Classifier: Programming Language :: Python :: 3
Classifier: Programming Language :: Python :: 3.4
Classifier: Programming Language :: Python :: 3.5
Classifier: Programming Language :: Python :: 3.6
Requires-Dist: requests
